tsfy/__init__.py
tsfy/datetime.py
tsfy-0.4.0.dist-info/WHEEL
tsfy-0.4.0.dist-info/METADATA
tsfy-0.4.0.dist-info/RECORD
